google/cloud/backupdr/__init__.py
google/cloud/backupdr/gapic_version.py
google/cloud/backupdr/py.typed
google/cloud/backupdr_v1/__init__.py
google/cloud/backupdr_v1/gapic_metadata.json
google/cloud/backupdr_v1/gapic_version.py
google/cloud/backupdr_v1/py.typed
google/cloud/backupdr_v1/services/__init__.py
google/cloud/backupdr_v1/services/backup_dr/__init__.py
google/cloud/backupdr_v1/services/backup_dr/async_client.py
google/cloud/backupdr_v1/services/backup_dr/client.py
google/cloud/backupdr_v1/services/backup_dr/pagers.py
google/cloud/backupdr_v1/services/backup_dr/transports/__init__.py
google/cloud/backupdr_v1/services/backup_dr/transports/base.py
google/cloud/backupdr_v1/services/backup_dr/transports/grpc.py
google/cloud/backupdr_v1/services/backup_dr/transports/grpc_asyncio.py
google/cloud/backupdr_v1/services/backup_dr/transports/rest.py
google/cloud/backupdr_v1/services/backup_dr/transports/rest_base.py
google/cloud/backupdr_v1/services/backup_dr_protection_summary/__init__.py
google/cloud/backupdr_v1/services/backup_dr_protection_summary/async_client.py
google/cloud/backupdr_v1/services/backup_dr_protection_summary/client.py
google/cloud/backupdr_v1/services/backup_dr_protection_summary/pagers.py
google/cloud/backupdr_v1/services/backup_dr_protection_summary/transports/__init__.py
google/cloud/backupdr_v1/services/backup_dr_protection_summary/transports/base.py
google/cloud/backupdr_v1/services/backup_dr_protection_summary/transports/grpc.py
google/cloud/backupdr_v1/services/backup_dr_protection_summary/transports/grpc_asyncio.py
google/cloud/backupdr_v1/services/backup_dr_protection_summary/transports/rest.py
google/cloud/backupdr_v1/services/backup_dr_protection_summary/transports/rest_base.py
google/cloud/backupdr_v1/types/__init__.py
google/cloud/backupdr_v1/types/backupdr.py
google/cloud/backupdr_v1/types/backupplan.py
google/cloud/backupdr_v1/types/backupplanassociation.py
google/cloud/backupdr_v1/types/backupvault.py
google_cloud_backupdr-0.7.0.dist-info/licenses/LICENSE
google_cloud_backupdr-0.7.0.dist-info/METADATA
google_cloud_backupdr-0.7.0.dist-info/WHEEL
google_cloud_backupdr-0.7.0.dist-info/top_level.txt
google_cloud_backupdr-0.7.0.dist-info/RECORD
